<bar id="top-users">
	<title>GNOME</title>

	<item href="http://www.gnome.org/about/">
		<title>About GNOME</title>
	</item>

	<item href="http://www.gnome.org/start/stable/">
		<title>Download</title>
	</item>

	<item href="http://www.gnome.org/">
		<title>Users</title>
	</item>

	<item href="http://art.gnome.org/">
		<title>Art &amp; Themes</title>
	</item>

	<item href="http://developer.gnome.org/">
		<title>Developers</title>
	</item>

	<item href="http://foundation.gnome.org/">
		<title>Foundation</title>
	</item>

	<item href="http://www.gnome.org/contact/">
		<title>Contact</title>
	</item>
</bar>
